hello_geo/__init__.py
hello_geo/common.py
hello_geo/hello_geo.py
hello_geo-0.0.3.dist-info/LICENSE
hello_geo-0.0.3.dist-info/METADATA
hello_geo-0.0.3.dist-info/WHEEL
hello_geo-0.0.3.dist-info/entry_points.txt
hello_geo-0.0.3.dist-info/top_level.txt
hello_geo-0.0.3.dist-info/RECORD
