Metadata-Version: 2.1
Name: hello-geo
Version: 0.0.3
Summary: A Python package demo
Author-email: Qiusheng Wu <giswqs@gmail.com>
License: MIT
Project-URL: Homepage, https://github.com/giswqs/hello-geo
Keywords: hello-geo
Classifier: Intended Audience :: Developers
Classifier: License :: OSI Approved :: MIT License
Classifier: Natural Language :: English
Classifier: Programming Language :: Python :: 3.8
Classifier: Programming Language :: Python :: 3.9
Classifier: Programming Language :: Python :: 3.10
Classifier: Programming Language :: Python :: 3.11
Classifier: Programming Language :: Python :: 3.12
Requires-Python: >=3.8
License-File: LICENSE
Requires-Dist: numpy
Provides-Extra: all
Requires-Dist: hello-geo[extra] ; extra == 'all'
Provides-Extra: extra
Requires-Dist: pandas ; extra == 'extra'
